{
  "@context": "http://iiif.io/api/presentation/2/context.json",
  "@id": "https://colenda.library.upenn.edu/items/ark:/81431/p3d21s460/manifest",
  "@type": "sc:Manifest",
  "label": "Letter; Meldola, David; Leeser, Isaac, Rev.; London, United Kingdom; 29 November 1851",
  "attribution": "Provided by the University of Pennsylvania Libraries.",
  "viewingHint": "individuals",
  "viewingDirection": "left-to-right",
  "metadata": [
    {
      "label": "Available Online",
      "value": [
        "https://colenda.library.upenn.edu/catalog/81431-p3d21s460"
      ]
    },
    {
      "label": "Title",
      "value": [
        "Letter; Meldola, David; Leeser, Isaac, Rev.; London, United Kingdom; 29 November 1851"
      ]
    },
    {
      "label": "Name",
      "value": [
        "Meldola, David, 1797-1853",
        "Leeser, Isaac"
      ]
    },
    {
      "label": "Date",
      "value": [
        "1851-11-29",
        "29 November 5611"
      ]
    },
    {
      "label": "Collection",
      "value": [
        "Isaac Leeser Collection at the Herbert D. Katz Center for Advanced Judaic Studies (University of Pennsylvania)"
      ]
    },
    {
      "label": "Item Type",
      "value": [
        "Text"
      ]
    },
    {
      "label": "Physical Format",
      "value": [
        "letters (correspondence)"
      ]
    },
    {
      "label": "Extent",
      "value": [
        "Letter"
      ]
    },
    {
      "label": "Language",
      "value": [
        "English",
        "Hebrew"
      ]
    },
    {
      "label": "Note",
      "value": [
        "2 pages on 2 sheets",
        "Issac Leeser Collection at the Herbert D. Katz Center for Advanced Judaic Studies (University of Pennsylvania)"
      ]
    },
    {
      "label": "Relation",
      "value": [
        "https://find.library.upenn.edu/catalog/9924408973503681"
      ]
    },
    {
      "label": "Geographic Subject",
      "value": [
        "United Kingdom -- London",
        "United Kingdom",
        "United States -- Pennsylvania -- Philadelphia",
        "United States -- Pennsylvania"
      ]
    },
    {
      "label": "Physical Location",
      "value": [
        "Arc.MS.2"
      ]
    },
    {
      "label": "Provenance",
      "value": [
        "Transfer of Custody from the Hebrew Education Society, 10 March 1913, to the Library of the Dropsie College for Hebrew and Cognate Learning."
      ]
    },
    {
      "label": "Rights",
      "value": [
        "http://rightsstatements.org/vocab/NoC-US/1.0/"
      ]
    },
    {
      "label": "Identifier",
      "value": [
        "LSDCBx1FF8_70"
      ]
    }
  ],
  "thumbnail": {
    "@id": "https://iiif-images.library.upenn.edu/iiif/2/498bbfd2-547a-4676-abdc-496ba53039b9%2Faccess/full/!200,200/0/default.jpg",
    "service": {
      "@context": "http://iiif.io/api/image/2/context.json",
      "@id": "https://iiif-images.library.upenn.edu/iiif/2/498bbfd2-547a-4676-abdc-496ba53039b9%2Faccess",
      "profile": "http://iiif.io/api/image/2/level2.json"
    }
  },
  "sequences": [
    {
      "@id": "https://colenda.library.upenn.edu/items/ark:/81431/p3d21s460/sequence/normal",
      "@type": "sc:Sequence",
      "label": "Current order",
      "rendering": [
        {
          "@id": "https://colenda.library.upenn.edu/items/ark:/81431/p3d21s460/pdf",
          "label": "Download PDF",
          "format": "application/pdf"
        }
      ],
      "canvases": [
        {
          "@id": "https://colenda.library.upenn.edu/items/ark:/81431/p3d21s460/canvas/p1",
          "@type": "sc:Canvas",
          "label": "1",
          "height": 4530,
          "width": 3602,
          "images": [
            {
              "@type": "oa:Annotation",
              "motivation": "sc:painting",
              "resource": {
                "@id": "https://iiif-images.library.upenn.edu/iiif/2/498bbfd2-547a-4676-abdc-496ba53039b9%2Faccess/full/!200,200/0/default.jpg",
                "@type": "dctypes:Image",
                "format": "image/jpeg",
                "width": 3602,
                "height": 4530,
                "service": {
                  "@context": "http://iiif.io/api/image/2/context.json",
                  "@id": "https://iiif-images.library.upenn.edu/iiif/2/498bbfd2-547a-4676-abdc-496ba53039b9%2Faccess",
                  "profile": "http://iiif.io/api/image/2/level2.json"
                }
              },
              "on": "https://colenda.library.upenn.edu/items/ark:/81431/p3d21s460/canvas/p1"
            }
          ],
          "rendering": [
            {
              "@id": "https://colenda.library.upenn.edu/items/ark:/81431/p3d21s460/assets/498bbfd2-547a-4676-abdc-496ba53039b9/original",
              "label": "Original File - 49.2 MB",
              "format": "image/tiff"
            }
          ],
          "annotations": [
            {
              "id": "https://colenda.library.upenn.edu/items/ark:/81431/p3d21s460/canvas/p1/annopage",
              "type": "AnnotationPage",
              "items": [
                {
                  "id": "https://colenda.library.upenn.edu/items/ark:/81431/p3d21s460/manifest/annotation/p1",
                  "type": "Annotation",
                  "motivation": "commenting",
                  "body": {
                    "type": "TextualBody",
                    "value": "\n                              <p rend=\"indent(9)\">\n                                        <placeName>London</placeName>\n                                        <date>29th Novr 5611</date>\n                              </p>\n                              <p rend=\"indent(10)\">\n                                        <placeName>6 Great Alie St. Goodman's fields</placeName>\n                              </p>\n                              <p rend=\"indent(8)\">\n                                        <add>כ\"ד כסלו ש' לא תיר\"א מהם</add>\n                              </p>\n                              <p rend=\"indent(1)\">Revd &amp; Dear Sir/</p>\n                              <p rend=\"indent(4)\">I am quite ashamed of my conduct towards<lb/> you\n                                        and do confess <add>בושתי וגם נכלמתי</add> for not replying\n                                        to your last communication<lb/> to me, as well as for the\n                                        review of the \"way of Faith\" and for your friendly\n                                        expressions<lb/> I feel indebted to you, but sufficient is\n                                        to express my sorrow, and that an alarming<lb/> complaint\n                                        was my preventative for so doing to a man of that high\n                                        esteem, regard,<lb/> &amp; veneration I hold for your high\n                                        talents and true learning (<add>חטאתי</add>), ever since I\n                                        first had<lb/> the satisfaction of perusing your scientific\n                                        writings, but since <add>מוצאי כפור</add>\n                                        <date>5610</date> I was attacked<lb/> with a severe cold\n                                        which gradually brought on an attack in the wind-pipe &amp;\n                                        which<lb/> actually despaired me causing some alarm till\n                                        very lately which with care &amp; attention<lb/> blessed be\n                                        God am quite recover'd, however for the present we must\n                                        leave further details, it is to<lb/> me a more important\n                                        subject on which I address you now, With truly painful\n                                        sorrows<lb/> I have seen in the Jewish Chronicle the place\n                                        of <add>חזן</add> vacant advertising for one, I must<lb/>\n                                        solemnly declare to you that I know nothing of the matter in\n                                        any way whatever,</p>\n                              <p rend=\"align center\">but some time since <sic>learnt</sic> that\n                                        there were some trifling</p>\n                              <p rend=\"align center\">differences but matters would be arranged which\n                                        gave</p>\n                              <p rend=\"align center\">me much gratification; of course this newly\n                                        advertisement astonished</p>\n                              <p>me, now dear sir it has ever been with me a maxim <add>אלא ליבכם\n                                                  בתחום שאינו שלי</add> but in the present<lb/> case\n                                        I must, it is most sacred with me <add>איש את רעהו יעזרו\n                                                  ולאחיו יאמר חזק</add> and as having been for a\n                                        number<lb/> of years <add>אב בית דין ומ\"ז</add> of the first\n                                        Portuguese Congregation in <placeName>Europe</placeName>,\n                                        also recognized by all<lb/> universities\n                                                  <placeName>Italy</placeName>,\n                                                  <placeName>Germany</placeName>,\n                                                  <placeName>Turkey</placeName>, <placeName>Holy\n                                                  land</placeName>, as <add>מוחזק לבר אוריין ובר\n                                                  אבהן ומורה בישראל</add>,<lb/> and, as the\n                                        descendant of that family which for the last 500 years have\n                                        been I consider<lb/> myself in duty bound to interfere &amp;\n                                        settle matters in your favour, after you have served<lb/>\n                                        them so many years sown the seed of knowledge &amp; wisdom,\n                                        such an action ought not<lb/> to be done to a great man of\n                                        your valuable erudition, would my health permit I<lb/> would\n                                        most willingly cross the <placeName>Great Sea</placeName> to\n                                        serve you &amp; put them to rights <del>and</del><lb/>\n                                        <sic>shewing</sic> them <add>and, as the descendant of that\n                                                  family which for the last 500 years have been I\n                                                  consider רבני הדור</add> pray without any loss of\n                                        time as a brother Israelite, &amp; friend in the<lb/> field\n                                        of literature reply to my letter, and in the greatest\n                                        confidence let me know how I can<lb/> serve you and to be of\n                                        use to you, I beg that you, &amp; they, will give in a\n                                        little in the existing differences,</p>\n                              "
                  },
                  "target": "https://colenda.library.upenn.edu/items/ark:/81431/p3d21s460/canvas/p1"
                }
              ]
            }
          ]
        },
        {
          "@id": "https://colenda.library.upenn.edu/items/ark:/81431/p3d21s460/canvas/p2",
          "@type": "sc:Canvas",
          "label": "2",
          "height": 3602,
          "width": 4530,
          "images": [
            {
              "@type": "oa:Annotation",
              "motivation": "sc:painting",
              "resource": {
                "@id": "https://iiif-images.library.upenn.edu/iiif/2/ac52cd53-7cb6-457f-9e73-d1dcd2422f7a%2Faccess/full/!200,200/0/default.jpg",
                "@type": "dctypes:Image",
                "format": "image/jpeg",
                "width": 4530,
                "height": 3602,
                "service": {
                  "@context": "http://iiif.io/api/image/2/context.json",
                  "@id": "https://iiif-images.library.upenn.edu/iiif/2/ac52cd53-7cb6-457f-9e73-d1dcd2422f7a%2Faccess",
                  "profile": "http://iiif.io/api/image/2/level2.json"
                }
              },
              "on": "https://colenda.library.upenn.edu/items/ark:/81431/p3d21s460/canvas/p2"
            }
          ],
          "rendering": [
            {
              "@id": "https://colenda.library.upenn.edu/items/ark:/81431/p3d21s460/assets/ac52cd53-7cb6-457f-9e73-d1dcd2422f7a/original",
              "label": "Original File - 49.2 MB",
              "format": "image/tiff"
            }
          ],
          "annotations": [
            {
              "id": "https://colenda.library.upenn.edu/items/ark:/81431/p3d21s460/canvas/p2/annopage",
              "type": "AnnotationPage",
              "items": [
                {
                  "id": "https://colenda.library.upenn.edu/items/ark:/81431/p3d21s460/manifest/annotation/p2",
                  "type": "Annotation",
                  "motivation": "commenting",
                  "body": {
                    "type": "TextualBody",
                    "value": "\n                              <p>I have laid before me many important cases from all parts to decide\n                                        upon <add>כי כן לא יעשה בישראל</add><lb/> and I am not\n                                        fearful that this will also be one I may succeed <add>לפשר\n                                                  דבר ולתווך השלום</add>, they may advertise here\n                                        but<lb/> they <del>will</del> can only find as\n                                                  <persName>Leeser's</persName> old shoes, <hi\n                                                  rend=\"underline\">all I say is in confidence</hi>.\n                                        You may make use of my<lb/> name in any way it can be of use\n                                        to you. You may mention to a <persName>Mr A: Hart</persName>\n                                        &amp; another<lb/> gent<hi rend=\"sup\">n</hi>. whom I have\n                                        seen that application must be made to them, not to be in\n                                        such a hurry<lb/> and to allow me to address them a truly\n                                        pastoral letter in your favour, as a true disciple<lb/> of\n                                                  <persName>Aaron</persName>\n                                        <add>בע\"ה</add> and as the son and Disciple of that immortal\n                                        father acknowledged<lb/> by all in 4 parts of the globe\n                                                  <add>אוהב שלום ורודף שלום</add>. I am determined\n                                        to serve you &amp; seek this important<lb/> blessing <add>א'\n                                                  מיחידי וגדולי הדור הישן</add> and not to be\n                                        allowed for the sake of a few tempers to <sic>supress</sic>\n                                        it. Favour me<lb/> with an immediate answer &amp; trust you\n                                        will hearken unto my voice do not abandon it,<lb/> wishing\n                                        you with all my heart every blessing <add>שלום</add> with\n                                        all esteem<lb/> I am Revd. &amp; Dear Sir</p>\n                              <p rend=\"indent(1)\">Yours very faithfully</p>\n                              <p rend=\"indent(2)\">\n                                        <persName role=\"author\">David Meldola</persName>\n                              </p>\n                              <p>It is peace and peace only I seek for,<lb/> trusting that as a\n                                                  gent<hi rend=\"sup\">n</hi>. you will keep a secret\n                                        such,<lb/> terms which I wrote you confidentially; our friend<lb/>\n                                        <persName>Hasone Pisa's</persName> best respects to you\n                                        &amp; shall be happy to hear from you <add>וכל אשר אתה עושה\n                                                  ה' מצליח</add></p>\n                              <p>\n                                        <addressee>Revd. Isaac Leeser</addressee>\n                              </p>\n                              <p rend=\"indent(1)\">\n                                        <placeName>Philadelphia</placeName>\n                              </p>\n                    </body>\n          </text>\n</TEI>\n"
                  },
                  "target": "https://colenda.library.upenn.edu/items/ark:/81431/p3d21s460/canvas/p2"
                }
              ]
            }
          ]
        }
      ]
    }
  ]
}