{
  "@context": "http://iiif.io/api/presentation/2/context.json",
  "@id": "https://colenda.library.upenn.edu/items/ark:/81431/p3dv1d78p/manifest",
  "@type": "sc:Manifest",
  "label": "Letter; Peixotto, B. F.; Leeser, Isaac, Rev.; Cleveland, OH; 6 May 1857",
  "attribution": "Provided by the University of Pennsylvania Libraries.",
  "viewingHint": "individuals",
  "viewingDirection": "left-to-right",
  "metadata": [
    {
      "label": "Available Online",
      "value": [
        "https://colenda.library.upenn.edu/catalog/81431-p3dv1d78p"
      ]
    },
    {
      "label": "Title",
      "value": [
        "Letter; Peixotto, B. F.; Leeser, Isaac, Rev.; Cleveland, OH; 6 May 1857"
      ]
    },
    {
      "label": "Name",
      "value": [
        "Leeser, Isaac"
      ]
    },
    {
      "label": "Date",
      "value": [
        "1857-05-06",
        "6 May 5617"
      ]
    },
    {
      "label": "Collection",
      "value": [
        "Isaac Leeser Collection at the Herbert D. Katz Center for Advanced Judaic Studies (University of Pennsylvania)"
      ]
    },
    {
      "label": "Item Type",
      "value": [
        "Text"
      ]
    },
    {
      "label": "Physical Format",
      "value": [
        "letters (correspondence)"
      ]
    },
    {
      "label": "Extent",
      "value": [
        "Letter"
      ]
    },
    {
      "label": "Language",
      "value": [
        "English"
      ]
    },
    {
      "label": "Note",
      "value": [
        "4 pages on 2 sheets",
        "Issac Leeser Collection at the Herbert D. Katz Center for Advanced Judaic Studies (University of Pennsylvania)"
      ]
    },
    {
      "label": "Relation",
      "value": [
        "https://find.library.upenn.edu/catalog/9924408973503681"
      ]
    },
    {
      "label": "Geographic Subject",
      "value": [
        "United States -- Ohio -- Cleveland",
        "United States -- Ohio",
        "United States -- Pennsylvania -- Philadelphia",
        "United States -- Pennsylvania"
      ]
    },
    {
      "label": "Physical Location",
      "value": [
        "Arc.MS.2"
      ]
    },
    {
      "label": "Provenance",
      "value": [
        "Transfer of Custody from the Hebrew Education Society, 10 March 1913, to the Library of the Dropsie College for Hebrew and Cognate Learning."
      ]
    },
    {
      "label": "Rights",
      "value": [
        "http://rightsstatements.org/vocab/NoC-US/1.0/"
      ]
    },
    {
      "label": "Identifier",
      "value": [
        "LSDCBx2FF4_37"
      ]
    }
  ],
  "thumbnail": {
    "@id": "https://iiif-images.library.upenn.edu/iiif/2/1bd0432c-ebe3-4844-9833-9d18ae927ce1%2Faccess/full/!200,200/0/default.jpg",
    "service": {
      "@context": "http://iiif.io/api/image/2/context.json",
      "@id": "https://iiif-images.library.upenn.edu/iiif/2/1bd0432c-ebe3-4844-9833-9d18ae927ce1%2Faccess",
      "profile": "http://iiif.io/api/image/2/level2.json"
    }
  },
  "sequences": [
    {
      "@id": "https://colenda.library.upenn.edu/items/ark:/81431/p3dv1d78p/sequence/normal",
      "@type": "sc:Sequence",
      "label": "Current order",
      "rendering": [
        {
          "@id": "https://colenda.library.upenn.edu/items/ark:/81431/p3dv1d78p/pdf",
          "label": "Download PDF",
          "format": "application/pdf"
        }
      ],
      "canvases": [
        {
          "@id": "https://colenda.library.upenn.edu/items/ark:/81431/p3dv1d78p/canvas/p1",
          "@type": "sc:Canvas",
          "label": "1",
          "height": 4610,
          "width": 3734,
          "images": [
            {
              "@type": "oa:Annotation",
              "motivation": "sc:painting",
              "resource": {
                "@id": "https://iiif-images.library.upenn.edu/iiif/2/1bd0432c-ebe3-4844-9833-9d18ae927ce1%2Faccess/full/!200,200/0/default.jpg",
                "@type": "dctypes:Image",
                "format": "image/jpeg",
                "width": 3734,
                "height": 4610,
                "service": {
                  "@context": "http://iiif.io/api/image/2/context.json",
                  "@id": "https://iiif-images.library.upenn.edu/iiif/2/1bd0432c-ebe3-4844-9833-9d18ae927ce1%2Faccess",
                  "profile": "http://iiif.io/api/image/2/level2.json"
                }
              },
              "on": "https://colenda.library.upenn.edu/items/ark:/81431/p3dv1d78p/canvas/p1"
            }
          ],
          "rendering": [
            {
              "@id": "https://colenda.library.upenn.edu/items/ark:/81431/p3dv1d78p/assets/1bd0432c-ebe3-4844-9833-9d18ae927ce1/original",
              "label": "Original File - 51.6 MB",
              "format": "image/tiff"
            }
          ],
          "annotations": [
            {
              "id": "https://colenda.library.upenn.edu/items/ark:/81431/p3dv1d78p/canvas/p1/annopage",
              "type": "AnnotationPage",
              "items": [
                {
                  "id": "https://colenda.library.upenn.edu/items/ark:/81431/p3dv1d78p/manifest/annotation/p1",
                  "type": "Annotation",
                  "motivation": "commenting",
                  "body": {
                    "type": "TextualBody",
                    "value": "<p rend=\"align(right)\">\n                <placeName>Cleveland</placeName>\n                <date>May 6<hi rend=\"sup\">th</hi> 1857. 5617</date>\n            </p>\n            <p>Rev &amp; Dear Friend</p>\n            <p rend=\"indent(3)\">I am duly in receipt of<lb/> your esteemed favor bearing date of the\n                    <date>3d</date><lb/> inst this morning and regret that I am<lb/> in possession\n                of the desired information<lb/> that might otherwise delay an immediate<lb/> answer.\n                Our mutually valued friend <persName>Alfred<lb/> T. Jones Esq.</persName> wrote us a\n                very eloquent letter some<lb/> time since in reference to the subject you have<lb/>\n                ably advocated and the trial we then made<lb/> to obtain loans from our\n                co-religionist re-<lb/>-sulted only in upraidings and derision.</p>\n            <p rend=\"indent(1)\">Not I assure you without just cause. The<lb/> congregation to which\n                we belong is in debt<lb/> to the amount of $2000. for building &amp; balance<lb/> of\n                money due on lot It consists of only 20<lb/> members upon whom from the\n                beginning<lb/> all the responsibility and liability has<lb/> devolved. We have been\n                but recently threat<lb/>-ened with a suit of ejectment which<lb/> caused us all to\n                bleed to our uttermost pe<lb/>-cuniarily the poorest among us advancing<lb/> a $100.\n                but we still have the heavy<lb/> burden of $2000 hanging o'er our necks<lb/> and\n                weighing us down with more</p>"
                  },
                  "target": "https://colenda.library.upenn.edu/items/ark:/81431/p3dv1d78p/canvas/p1"
                }
              ]
            }
          ]
        },
        {
          "@id": "https://colenda.library.upenn.edu/items/ark:/81431/p3dv1d78p/canvas/p2",
          "@type": "sc:Canvas",
          "label": "2",
          "height": 4610,
          "width": 3734,
          "images": [
            {
              "@type": "oa:Annotation",
              "motivation": "sc:painting",
              "resource": {
                "@id": "https://iiif-images.library.upenn.edu/iiif/2/c00d8f8a-e9ed-47e9-8f24-3d629f7e423b%2Faccess/full/!200,200/0/default.jpg",
                "@type": "dctypes:Image",
                "format": "image/jpeg",
                "width": 3734,
                "height": 4610,
                "service": {
                  "@context": "http://iiif.io/api/image/2/context.json",
                  "@id": "https://iiif-images.library.upenn.edu/iiif/2/c00d8f8a-e9ed-47e9-8f24-3d629f7e423b%2Faccess",
                  "profile": "http://iiif.io/api/image/2/level2.json"
                }
              },
              "on": "https://colenda.library.upenn.edu/items/ark:/81431/p3dv1d78p/canvas/p2"
            }
          ],
          "rendering": [
            {
              "@id": "https://colenda.library.upenn.edu/items/ark:/81431/p3dv1d78p/assets/c00d8f8a-e9ed-47e9-8f24-3d629f7e423b/original",
              "label": "Original File - 51.6 MB",
              "format": "image/tiff"
            }
          ],
          "annotations": [
            {
              "id": "https://colenda.library.upenn.edu/items/ark:/81431/p3dv1d78p/canvas/p2/annopage",
              "type": "AnnotationPage",
              "items": [
                {
                  "id": "https://colenda.library.upenn.edu/items/ark:/81431/p3dv1d78p/manifest/annotation/p2",
                  "type": "Annotation",
                  "motivation": "commenting",
                  "body": {
                    "type": "TextualBody",
                    "value": "<p>or less anxiety. Under these circumstances the idea<lb/> of contributing to the aid\n                of others is almost scow-<lb/>-led at, however charity-like. But this arises\n                from<lb/> a two-fold reason, first <hi rend=\"underline\">our own burdens</hi>,\n                secondly<lb/> the remembrance of the treatment we received<lb/> when we made an\n                appeal to our brethren<lb/> in <placeName>Philadelphia</placeName> and\n                    <placeName>N.Y.</placeName> where our mission-<lb/>ary or rather messenger after\n                spending a<lb/> whole month succeeded in raising only the<lb/> paltry sum of $160.\n                Think of the mighty cities<lb/> of <placeName>N. Y.</placeName> &amp;\n                    <placeName>Phila</placeName> combinedly giving only $160!<lb/> A private\n                donation would have amounted to<lb/> more if actuated by the proper spirit and<lb/>\n                ability! No, my dear Sir I regret to say<lb/> there is not the slightest prospect of\n                raising<lb/> a dollar in aid of the laudable object you<lb/> warmly advocate, it\n                would be a great source<lb/> of happiness to me to be the means in however<lb/>\n                slight a manner to assist our co-religionists<lb/> in <placeName>Phila</placeName>\n                to place you at the head of a prosperous congre-<lb/>gation, but lacking the\n                necessary power I must<lb/> be placed among those of your friends who<lb/> have all\n                the will but none of the ability.</p>\n            <p rend=\"indent(1)\">Your return to the ministry will be<lb/> warmly hailed by your\n                brethren throughout<lb/> the Union and considered by all your true<lb/> friends as\n                an eventual triumph. How grati</p>"
                  },
                  "target": "https://colenda.library.upenn.edu/items/ark:/81431/p3dv1d78p/canvas/p2"
                }
              ]
            }
          ]
        },
        {
          "@id": "https://colenda.library.upenn.edu/items/ark:/81431/p3dv1d78p/canvas/p3",
          "@type": "sc:Canvas",
          "label": "3",
          "height": 4610,
          "width": 3734,
          "images": [
            {
              "@type": "oa:Annotation",
              "motivation": "sc:painting",
              "resource": {
                "@id": "https://iiif-images.library.upenn.edu/iiif/2/d22dc997-89d4-467a-8596-8ca7408d586b%2Faccess/full/!200,200/0/default.jpg",
                "@type": "dctypes:Image",
                "format": "image/jpeg",
                "width": 3734,
                "height": 4610,
                "service": {
                  "@context": "http://iiif.io/api/image/2/context.json",
                  "@id": "https://iiif-images.library.upenn.edu/iiif/2/d22dc997-89d4-467a-8596-8ca7408d586b%2Faccess",
                  "profile": "http://iiif.io/api/image/2/level2.json"
                }
              },
              "on": "https://colenda.library.upenn.edu/items/ark:/81431/p3dv1d78p/canvas/p3"
            }
          ],
          "rendering": [
            {
              "@id": "https://colenda.library.upenn.edu/items/ark:/81431/p3dv1d78p/assets/d22dc997-89d4-467a-8596-8ca7408d586b/original",
              "label": "Original File - 51.6 MB",
              "format": "image/tiff"
            }
          ],
          "annotations": [
            {
              "id": "https://colenda.library.upenn.edu/items/ark:/81431/p3dv1d78p/canvas/p3/annopage",
              "type": "AnnotationPage",
              "items": [
                {
                  "id": "https://colenda.library.upenn.edu/items/ark:/81431/p3dv1d78p/manifest/annotation/p3",
                  "type": "Annotation",
                  "motivation": "commenting",
                  "body": {
                    "type": "TextualBody",
                    "value": "<p>-fying<lb/> it must be to you after so many long years to<lb/> once more and that to\n                in <placeName>Philadelphia</placeName> assume<lb/> the exalted office it has been\n                your destiny to<lb/> so ably fill, permit me to congratulate you.</p>\n            <p rend=\"indent(1)\">I cannot express to you the real plea-<lb/>sure—the very <hi\n                    rend=\"underline\">thought</hi> of your return affords<lb/> to my heart, believe\n                me I hail it with no<lb/> ordinary emotions of pride and gratification<lb/> of\n                course at present perhaps forever the “Advo-<lb/>-cate” will be abandoned—your\n                ministerial<lb/> duties and your editorial not permitting ad<lb/>-ditional—at least\n                at present, perhaps it is<lb/> as well, the generation to come will be a more<lb/>\n                intelligent one. I mean of our people in this<lb/> country, and they will require a\n                literature<lb/> of their own. I shall forthwith consti-<lb/>tute myself your active\n                agent here for your<lb/> admirable journal the occident and as<lb/> meet “our\n                people” weekly now at the lodge,<lb/> being a member of the I.O.BB. I shall\n                have<lb/> opportunities which shall not be lost. I<lb/> begin by sending you the\n                name of<lb/>\n                <persName>D. Cauffman</persName> to whom from <date>1<hi rend=\"sup\">st</hi> of\n                    May</date><lb/> you may send the Occident <del>for one year</del><lb/> I shall\n                exert myself in your further<lb/> behalf in this respect on every occasion<lb/> and\n                the pleasure of this aiding to</p>"
                  },
                  "target": "https://colenda.library.upenn.edu/items/ark:/81431/p3dv1d78p/canvas/p3"
                }
              ]
            }
          ]
        },
        {
          "@id": "https://colenda.library.upenn.edu/items/ark:/81431/p3dv1d78p/canvas/p4",
          "@type": "sc:Canvas",
          "label": "4",
          "height": 4610,
          "width": 3734,
          "images": [
            {
              "@type": "oa:Annotation",
              "motivation": "sc:painting",
              "resource": {
                "@id": "https://iiif-images.library.upenn.edu/iiif/2/4e906708-f2d7-414b-8fa9-bee3ca0b3ed7%2Faccess/full/!200,200/0/default.jpg",
                "@type": "dctypes:Image",
                "format": "image/jpeg",
                "width": 3734,
                "height": 4610,
                "service": {
                  "@context": "http://iiif.io/api/image/2/context.json",
                  "@id": "https://iiif-images.library.upenn.edu/iiif/2/4e906708-f2d7-414b-8fa9-bee3ca0b3ed7%2Faccess",
                  "profile": "http://iiif.io/api/image/2/level2.json"
                }
              },
              "on": "https://colenda.library.upenn.edu/items/ark:/81431/p3dv1d78p/canvas/p4"
            }
          ],
          "rendering": [
            {
              "@id": "https://colenda.library.upenn.edu/items/ark:/81431/p3dv1d78p/assets/4e906708-f2d7-414b-8fa9-bee3ca0b3ed7/original",
              "label": "Original File - 51.6 MB",
              "format": "image/tiff"
            }
          ],
          "annotations": [
            {
              "id": "https://colenda.library.upenn.edu/items/ark:/81431/p3dv1d78p/canvas/p4/annopage",
              "type": "AnnotationPage",
              "items": [
                {
                  "id": "https://colenda.library.upenn.edu/items/ark:/81431/p3dv1d78p/manifest/annotation/p4",
                  "type": "Annotation",
                  "motivation": "commenting",
                  "body": {
                    "type": "TextualBody",
                    "value": "<p>disseminate the doctrines promulgated <del>in you</del><lb/> through your journal,\n                will be “sweet recompense<lb/> for all my labors.” It may be that I may<lb/> in some\n                of my “inspired moments” send<lb/> you a fledgling for the grave columns of<lb/> the\n                Occident but it will much depend<lb/> upon “time” and the “will” to do anything<lb/>\n                that smacks of literary recreation or labor.</p>\n            <p rend=\"indent(1)\">Your friends here who esteem you so warm<lb/>-ly beg me to assure\n                you of the gratification<lb/> your return to the pulpit will afford<lb/> them. Both\n                    <persName>Mr &amp; Mrs Davis</persName> desire (with<lb/> my Brother &amp;\n                    <add>?</add>) to be kindly<lb/> remembered. Thank God our little ones<lb/> have\n                come through the “fire &amp; water” of their<lb/> recent long &amp; painful not to\n                say serious<lb/> sickness in safety the gloom that has<lb/> so long hung over our\n                household is fast<lb/> disappearing under the blessed and<lb/> benigrant<add>?</add>\n                rays of returning Health &amp; Sunshine<lb/> With renewed assurances of esteem\n                and<lb/> regard believe me</p>\n            <p rend=\"indent(8)\">Very truly &amp; warmly</p>\n            <p rend=\"indent(9)\">your friend</p>\n            <p rend=\"indent(9)\">\n                <persName role=\"author\">B F. Peixotto</persName>\n            </p>\n        </body>\n    </text>\n</TEI>"
                  },
                  "target": "https://colenda.library.upenn.edu/items/ark:/81431/p3dv1d78p/canvas/p4"
                }
              ]
            }
          ]
        }
      ]
    }
  ]
}